openfast_python/openfast/CaseGen_General.py
openfast_python/openfast/FAST_post.py
openfast_python/openfast/FAST_reader.py
openfast_python/openfast/FAST_vars_out.py
openfast_python/openfast/FAST_wrapper.py
openfast_python/openfast/FAST_writer.py
openfast_python/openfast/FileTools.py
openfast_python/openfast/IEC_CoeherentGusts.py
openfast_python/openfast/LinearFAST.py
openfast_python/openfast/StC_defaults.py
openfast_python/openfast/__init__.py
openfast_python/openfast/create_output_vars.py
openfast_python/openfast/openfast_library.py
openfast_python/openfast/runFAST_pywrapper.py
openfast_python/openfast/test/test_OF_utils.py
openfast_python/openfast/test/test_data/OpenFAST_models/BAR_00/Airfoils/OpenFAST_BAR_00_AF00_Coords.txt
openfast_python/openfast/test/test_data/OpenFAST_models/BAR_00/Airfoils/OpenFAST_BAR_00_AF01_Coords.txt
openfast_python/openfast/test/test_data/OpenFAST_models/BAR_00/Airfoils/OpenFAST_BAR_00_AF02_Coords.txt
openfast_python/openfast/test/test_data/OpenFAST_models/BAR_00/Airfoils/OpenFAST_BAR_00_AF03_Coords.txt
openfast_python/openfast/test/test_data/OpenFAST_models/BAR_00/Airfoils/OpenFAST_BAR_00_AF04_Coords.txt
openfast_python/openfast/test/test_data/OpenFAST_models/BAR_00/Airfoils/OpenFAST_BAR_00_AF05_Coords.txt
openfast_python/openfast/test/test_data/OpenFAST_models/BAR_00/Airfoils/OpenFAST_BAR_00_AF06_Coords.txt
openfast_python/openfast/test/test_data/OpenFAST_models/BAR_00/Airfoils/OpenFAST_BAR_00_AF07_Coords.txt
openfast_python/openfast/test/test_data/OpenFAST_models/BAR_00/Airfoils/OpenFAST_BAR_00_AF08_Coords.txt
openfast_python/openfast/test/test_data/OpenFAST_models/BAR_00/Airfoils/OpenFAST_BAR_00_AF09_Coords.txt
openfast_python/openfast/test/test_data/OpenFAST_models/BAR_00/Airfoils/OpenFAST_BAR_00_AF10_Coords.txt
openfast_python/openfast/test/test_data/OpenFAST_models/BAR_00/Airfoils/OpenFAST_BAR_00_AF11_Coords.txt
openfast_python/openfast/test/test_data/OpenFAST_models/BAR_00/Airfoils/OpenFAST_BAR_00_AF12_Coords.txt
octue_openfast-3.5.4.dist-info/LICENSE
octue_openfast-3.5.4.dist-info/METADATA
octue_openfast-3.5.4.dist-info/WHEEL
octue_openfast-3.5.4.dist-info/RECORD
