Metadata-Version: 2.1
Name: octue-openfast
Version: 3.5.4
Summary: Readers and writers for OpenFAST files.
Author: NREL WISDEM Team
Author-email: systems.engineering@nrel.gov
Requires-Python: >=3.9,<4.0
Classifier: Programming Language :: Python :: 3
Classifier: Programming Language :: Python :: 3.9
Classifier: Programming Language :: Python :: 3.10
Classifier: Programming Language :: Python :: 3.11
Classifier: Programming Language :: Python :: 3.12
Requires-Dist: numpy (>=1,<2)
Requires-Dist: pandas (>=2,<3)
Requires-Dist: pcrunch (>=1.1.0,<2.0.0)
Requires-Dist: rosco (>=2.9,<3.0)
Requires-Dist: ruamel_yaml (>=0.18,<0.19)
Requires-Dist: xlrd (>=2,<3)
